engine.cpython-37m-darwin.so
stalib/__init__.py
stalib/algorithms.py
stalib/conftest.py
stalib/templates.py
stalib/core/__init__.pxd
stalib/core/__init__.py
stalib/core/_algorithms.pxd
stalib/core/engine.cpp
stalib/core/engine.pyx
stalib/core/setup.py
stalib/core/algorithms/__init__.pxd
stalib/core/algorithms/ops.pxd
stalib/core/algorithms/search/search.cpp
stalib/core/algorithms/sort/sort.cpp
stalib/core/templates/__init__.pxd
stalib/core/templates/ops.pxd
stalib/errors/__init__.py
stalib/tests/__init__.py
stalib/tests/test_core_cython_entry.py
stalib/tests/test_errors.py
stalib/tests/test_search_algorithms.py
stalib/tests/test_sort_algorithms.py
stalib-0.1.1.dist-info/LICENSE
stalib-0.1.1.dist-info/METADATA
stalib-0.1.1.dist-info/WHEEL
stalib-0.1.1.dist-info/top_level.txt
stalib-0.1.1.dist-info/RECORD
