Metadata-Version: 2.1
Name: stalib
Version: 0.1.1
Summary: UNKNOWN
Home-page: https://github.com/sanoguzhan/STAlib
Author: Oguzhan San
Author-email: sanoguzhan@hotmail.com
License: MIT
Keywords: Template,Cython,Algorithms,C++,Sort,Search,Data Containers
Platform: UNKNOWN
Classifier: Development Status :: 3 - Alpha
Classifier: Intended Audience :: Developers
Classifier: Topic :: Software Development :: Build Tools
Classifier: License :: OSI Approved :: MIT License
Classifier: Natural Language :: English
Classifier: Programming Language :: Python :: 3
Classifier: Programming Language :: Python :: 3.4
Classifier: Programming Language :: Python :: 3.5
Classifier: Programming Language :: Python :: 3.6
Requires-Python: >=3.0
Requires-Dist: cython
Requires-Dist: matplotlib
Requires-Dist: Sphinx
Requires-Dist: wheel
Requires-Dist: tox
Requires-Dist: flake8
Requires-Dist: pytest
